pyreprimand.cpython-310-x86_64-linux-gnu.so
debug.py
RePrimAnd-1.7.dist-info/top_level.txt
RePrimAnd-1.7.dist-info/METADATA
RePrimAnd-1.7.dist-info/RECORD
RePrimAnd-1.7.dist-info/LICENSE
RePrimAnd-1.7.dist-info/WHEEL
RePrimAnd.libs/libgsl-e0b7bbb0.so.27.0.0
RePrimAnd.libs/libRePrimAnd-cebeea4c.so
RePrimAnd.libs/libhdf5-82cc1ca8.so.200.1.0
RePrimAnd.libs/libgslcblas-39367efd.so.0.0.0
