Metadata-Version: 2.1
Name: RePrimAnd
Version: 1.7
Summary: Library for handling equations of state for supranuclear matter, computing neutron star properties, and utilities for numerical relativity
Author-email: Wolfgang Kastaun <physik@fangwolg.de>
License: Copyright Notice and License Terms for the RePrimAnd library
Project-URL: homepage, https://github.com/wokast/RePrimAnd
Project-URL: documentation, https://wokast.github.io/RePrimAnd/index.html
Project-URL: repository, https://github.com
Requires-Python: >=3.7
License-File: LICENSE
Requires-Dist: numpy
